ckanext_collection-0.3.0-py3.9-nspkg.pth
ckanext/collection/__init__.py
ckanext/collection/ap_config.yaml
ckanext/collection/cli.py
ckanext/collection/config.py
ckanext/collection/config_declaration.yaml
ckanext/collection/helpers.py
ckanext/collection/interfaces.py
ckanext/collection/internal.py
ckanext/collection/plugin.py
ckanext/collection/shared.py
ckanext/collection/signals.py
ckanext/collection/types.py
ckanext/collection/views.py
ckanext/collection/assets/webassets.yml
ckanext/collection/assets/js/htmx-init-ckan-modules.js
ckanext/collection/assets/vendor/htmx.js
ckanext/collection/logic/__init__.py
ckanext/collection/logic/auth.py
ckanext/collection/templates/page.html
ckanext/collection/templates/collection/serialize/collection_explorer/main.html
ckanext/collection/templates/collection/serialize/db_explorer/main.html
ckanext/collection/templates/collection/serialize/explorer/main.html
ckanext/collection/templates/collection/serialize/html/main.html
ckanext/collection/templates/collection/serialize/html/record.html
ckanext/collection/templates/collection/serialize/htmx_table/counter.html
ckanext/collection/templates/collection/serialize/htmx_table/filter.html
ckanext/collection/templates/collection/serialize/htmx_table/form.html
ckanext/collection/templates/collection/serialize/htmx_table/main.html
ckanext/collection/templates/collection/serialize/htmx_table/pager.html
ckanext/collection/templates/collection/serialize/htmx_table/record.html
ckanext/collection/templates/collection/serialize/htmx_table/table.html
ckanext/collection/templates/collection/serialize/table/counter.html
ckanext/collection/templates/collection/serialize/table/filter.html
ckanext/collection/templates/collection/serialize/table/form.html
ckanext/collection/templates/collection/serialize/table/main.html
ckanext/collection/templates/collection/serialize/table/pager.html
ckanext/collection/templates/collection/serialize/table/record.html
ckanext_collection-0.3.0.dist-info/LICENSE
ckanext_collection-0.3.0.dist-info/METADATA
ckanext_collection-0.3.0.dist-info/WHEEL
ckanext_collection-0.3.0.dist-info/entry_points.txt
ckanext_collection-0.3.0.dist-info/namespace_packages.txt
ckanext_collection-0.3.0.dist-info/top_level.txt
ckanext_collection-0.3.0.dist-info/RECORD
